gst_calculator/Capital_Gains_Report_Generator .py
gst_calculator/Investment_Tax_Benefits_Calculator.py
gst_calculator/__init__.py
gst_calculator/bulk_income_tax_return.py
gst_calculator/business_tax.py
gst_calculator/gst_calculator.py
gst_calculator/income_tax.py
gst_calculator/tds_corporate.py
gst_calculator/tds_individual.py
gst_calculator/tempCodeRunnerFile.py
gst_calculator-0.1.dist-info/METADATA
gst_calculator-0.1.dist-info/WHEEL
gst_calculator-0.1.dist-info/top_level.txt
gst_calculator-0.1.dist-info/RECORD
